fdlogger/__init__.py
fdlogger/__main__.py
fdlogger/data/JetBrainsMono-Regular.ttf
fdlogger/data/MASTER.SCP
fdlogger/data/arrl_sect.dat
fdlogger/data/cwmacros_fd.txt
fdlogger/data/dialog.ui
fdlogger/data/fd_preferences.json
fdlogger/data/k6gte-fieldday.desktop
fdlogger/data/main.ui
fdlogger/data/opon.ui
fdlogger/data/settings.ui
fdlogger/data/startup.ui
fdlogger/icon/cloud_green.png
fdlogger/icon/cloud_grey.png
fdlogger/icon/cloud_red.png
fdlogger/icon/gear16x16.png
fdlogger/icon/k6gte-fdlogger.png
fdlogger/icon/logo.png
fdlogger/icon/radio.svg
fdlogger/icon/radio_green.png
fdlogger/icon/radio_grey.png
fdlogger/icon/radio_red.png
fdlogger/lib/__init__.py
fdlogger/lib/cat_interface.py
fdlogger/lib/cwinterface.py
fdlogger/lib/database.py
fdlogger/lib/edit_opon.py
fdlogger/lib/lookup.py
fdlogger/lib/n1mm.py
fdlogger/lib/settings.py
fdlogger/lib/version.py
fdlogger/lib/versiontest.py
fdlogger-25.8.19.dist-info/licenses/LICENSE
testing/inject_multicast.py
testing/inject_udp.py
testing/multicast_listener.py
testing/simulant.py
fdlogger-25.8.19.dist-info/METADATA
fdlogger-25.8.19.dist-info/WHEEL
fdlogger-25.8.19.dist-info/entry_points.txt
fdlogger-25.8.19.dist-info/top_level.txt
fdlogger-25.8.19.dist-info/RECORD
